mmWave/__init__.py
mmWave/droneRN.py
mmWave/highAccuracy.py
mmWave/lpdFDS.py
mmWave/lpdISK.py
mmWave/lpdISK_kv.py
mmWave/lpdISK_v2.py
mmWave/mrRadar.py
mmWave/obstacleDS.py
mmWave/pc3.py
mmWave/pc3OVH.py
mmWave/pc3_360.py
mmWave/pc3_fish.py
mmWave/pc3_oob.py
mmWave/pc3_v1884R.py
mmWave/pc3_v2.py
mmWave/pc3_vsd.py
mmWave/pc3_vsd_v2.py
mmWave/pc3d.py
mmWave/pc3d_kv.py
mmWave/pct.py
mmWave/people3D.py
mmWave/peopleMB.py
mmWave/roadwayTMD_kv.py
mmWave/srradar.py
mmWave/surfaceVD.py
mmWave/trafficMD.py
mmWave/trafficMD_I480.py
mmWave/trafficMD_kv.py
mmWave/vehicleOD.py
mmWave/vehicleODHeatMap.py
mmWave/vehicleODR.py
mmWave/vitalsign.py
mmWave/vitalsign_kv.py
mmwave-1.0.107.dist-info/METADATA
mmwave-1.0.107.dist-info/WHEEL
mmwave-1.0.107.dist-info/top_level.txt
mmwave-1.0.107.dist-info/RECORD
