Metadata-Version: 2.4
Name: mmWave
Version: 1.0.107
Summary: Joybien mmWave (Batman-101/201/301/501/601) library
Home-page: http://www.joybien.com
Download-URL: https://pypi.org/project/mmWave
Author: Bighead Chen
Author-email: zach_chen@joybien.com
License: MIT
Project-URL: API Source Code, https://github.com/bigheadG/mmWave
Classifier: Programming Language :: Python :: 3
Classifier: License :: OSI Approved :: MIT License
Classifier: Operating System :: OS Independent
Requires-Python: >=3.6
Dynamic: author
Dynamic: author-email
Dynamic: classifier
Dynamic: description
Dynamic: description-content-type
Dynamic: download-url
Dynamic: home-page
Dynamic: license
Dynamic: project-url
Dynamic: requires-python
Dynamic: summary
